constructional_diversity/__init__.py
constructional_diversity/extractor.py
constructional_diversity/setup.py
constructional_diversity-0.0.10.dist-info/METADATA
constructional_diversity-0.0.10.dist-info/WHEEL
constructional_diversity-0.0.10.dist-info/top_level.txt
constructional_diversity-0.0.10.dist-info/RECORD
