Metadata-Version: 2.4
Name: constructional-diversity
Version: 0.0.10
Summary: This is a package with which users can analyze constructional diversity, constructional complexity, and verbal diversity.
Home-page: https://pypi.org/project/constructional-diversity
Author: Haerim Hwang
Author-email: yayhaerim@gmail.com
License: MIT
Requires-Python: >=3.9
Requires-Dist: more_itertools
Requires-Dist: spacy
Requires-Dist: numpy
Requires-Dist: pandas
Requires-Dist: torch
Requires-Dist: openpyxl
Dynamic: author
Dynamic: author-email
Dynamic: description
Dynamic: description-content-type
Dynamic: home-page
Dynamic: license
Dynamic: requires-dist
Dynamic: requires-python
Dynamic: summary
